setup.py
data_preprocessing_lr_model/__init__.py
data_preprocessing_lr_model/data_preprocessing_lr_model.py
data_preprocessing_lr_model.egg-info/PKG-INFO
data_preprocessing_lr_model.egg-info/SOURCES.txt
data_preprocessing_lr_model.egg-info/dependency_links.txt
data_preprocessing_lr_model.egg-info/not-zip-safe
data_preprocessing_lr_model.egg-info/top_level.txt