Metadata-Version: 2.1
Name: data-preprocessing-lr-model
Version: 0.2
Summary: Deleting categorical variables, standardizing variables, checking multicolinearity and then building linear regression model (or ridge, lasso, elasticnet) and making predictions on her
Home-page: UNKNOWN
License: UNKNOWN
Platform: UNKNOWN
